{
  "products": [
    {
      "id": "a3699940-5f2b-4e02-8e42-a946a9e0b53a",
      "color": "White",
      "men": "true",
      "name": "Mens T-shirt",
      "price": "250",
      "sizeL": "true",
      "sizeM": "true",
      "sizeS": "true",
      "url": "https://assets.myntassets.com/dpr_1.5,q_60,w_400,c_limit,fl_progressive/assets/images/productimage/2019/12/12/1aab2a18-6774-4f83-b292-fe301755a3351576102551329-1.jpg"
    },
    {
      "id": "8aef3745-8d9f-4803-a28e-97700ac073ab",
      "color": "Black",
      "men": "true",
      "name": "Printed T-shirts",
      "price": "200",
      "sizeL": "true",
      "sizeM": "true",
      "sizeS": "true",
      "url": "https://assets.ajio.com/medias/sys_master/root/20220121/8pKF/61ea5b4baeb2695cdd24612b/-473Wx593H-461592493-multi-MODEL.jpg"
    },
    {
      "id": "db82ab22-1119-465c-879c-ce2321b5059d",
      "color": "Blue",
      "men": "true",
      "name": "Men's t-shirt Blue",
      "price": "400",
      "sizeL": "true",
      "sizeM": "true",
      "sizeS": "true",
      "url": "https://assets.ajio.com/medias/sys_master/root/20220121/XQUl/61ea5b98aeb2695cdd2466db/-473Wx593H-461575346-blue-MODEL.jpg"
    },
    {
      "id": "a17f8a96-9016-45ac-a4f0-b628eb90d620",
      "color": "Yellow",
      "men": "true",
      "name": "Men's plain yellow t-shirt",
      "price": "450",
      "sizeL": "true",
      "sizeM": "true",
      "sizeS": "true",
      "url": "https://m.media-amazon.com/images/I/514Ibqp2XZL._UX569_.jpg"
    },
    {
      "id": "129abbea-b19d-40ee-bc83-b0efcdbd93fc",
      "color": "Black",
      "men": "true",
      "name": "Oversized t-shirt",
      "price": "400",
      "sizeL": "",
      "sizeM": "true",
      "sizeS": "true",
      "url": "https://m.media-amazon.com/images/I/71QvZzrovaL._UL1500_.jpg"
    },
    {
      "id": "53bfff23-eb3e-4169-a8da-15dc3c5ad610",
      "color": "Brown",
      "men": "true",
      "name": "Mens's Brow T-shirt",
      "price": "250",
      "sizeL": "true",
      "sizeM": "true",
      "sizeS": "true",
      "url": "https://www.beyoung.in/api/cache/catalog/products/plain_new_update_images_2_5_2022/burgundy_plain_t-shirt_base_25_5_2022_400x533.jpg"
    },
    {
      "id": "3a939cd3-4a23-4400-aba5-78988702c713",
      "color": "Blue",
      "men": "true",
      "name": "Printed Blue-White T-shirt",
      "price": "400",
      "sizeL": "true",
      "sizeM": "true",
      "sizeS": "true",
      "url": "https://cdn.shopify.com/s/files/1/0752/6435/products/HERO-CROP_3403736d-8645-40ab-af3f-a60a812b9f28.jpg?v=1663857881"
    },
    {
      "id": "7639d123-a465-4280-ab18-a90fc7886336",
      "color": "Blue",
      "men": "true",
      "name": "Crew neck t-shirt",
      "price": "400",
      "sizeL": "true",
      "sizeM": "true",
      "sizeS": "true",
      "url": "https://encrypted-tbn0.gstatic.com/images?q=tbn:ANd9GcQm__08Pgqpextceh7ss5gPzna6HbKpD7DrAINPItT74yC5nTcCAwBhQwPj3fwez2FfoTI&usqp=CAU"
    },
    {
      "id": "33199ce6-43c5-4598-9ae7-5ef65d4059cb",
      "color": "Black",
      "men": "true",
      "name": "Men's sweat shirt",
      "price": "500",
      "sizeL": "true",
      "sizeM": "true",
      "sizeS": "true",
      "url": "https://assets.myntassets.com/dpr_1.5,q_60,w_400,c_limit,fl_progressive/assets/images/12377258/2020/9/11/ce1b7bcb-a65a-4eb0-a317-42ac02718f1e1599798741705UrbanoFashionPrintedMenRoundNeckDarkGreenT-Shirt1.jpg"
    },
    {
      "id": "cafb7365-ea00-4f0d-b68f-68e6ed2615e5",
      "color": "Pink",
      "men": "true",
      "name": "Men's Pink t-shirt",
      "price": "500",
      "sizeL": "true",
      "sizeM": "true",
      "sizeS": "true",
      "url": "https://assets.ajio.com/medias/sys_master/root/h6c/h08/12829356064798/-473Wx593H-460322907-purple-MODEL.jpg"
    },
    {
      "id": "6948fc90-c09e-4b61-a771-116913b52e25",
      "color": "white",
      "men": "true",
      "name": "Men's sweat shirt",
      "price": "500",
      "sizeL": "true",
      "sizeM": "true",
      "sizeS": "true",
      "url": "https://cdn.shopify.com/s/files/1/0082/3944/8160/products/190A4089_600x.progressive.jpg?v=1646651558"
    },
    {
      "id": "9fa85ac0-8d53-47f7-8c4c-bc48a0651bc0",
      "color": "Black",
      "men": "true",
      "name": "Men's sweat shirt",
      "price": "500",
      "sizeL": "true",
      "sizeM": "true",
      "sizeS": "true",
      "url": "https://encrypted-tbn0.gstatic.com/images?q=tbn:ANd9GcS_6Ch625kwRs_fLGun282M8PoKHICg6GCLXu4fCViV8iVL4pTdxeyC2wLgIX-tY9KUDzA&usqp=CAU"
    },
    {
      "id": "c31e5c15-7e96-4db3-831e-6cada1ba9983",
      "color": "Green",
      "men": "true",
      "name": "Men's crew neck t-shirt",
      "price": "400",
      "sizeL": "true",
      "sizeM": "true",
      "sizeS": "true",
      "url": "https://encrypted-tbn0.gstatic.com/images?q=tbn:ANd9GcRCZx86UGRzOKZMilzi0SXETHCaMMmU7Fc4Hg&usqp=CAU"
    },
    {
      "id": "415b5d94-2bb3-4094-89c5-e256e54def28",
      "color": "Purple",
      "men": "true",
      "name": "Printed t-shirt",
      "price": "500",
      "sizeL": "true",
      "sizeM": "true",
      "sizeS": "true",
      "url": "https://encrypted-tbn0.gstatic.com/images?q=tbn:ANd9GcQlICooUSDlEyM4ACetwTfLn2oIiksQmFkHRu4eYuXX3vxK_oh-LUW9xBlZ9xmbHdfcnLU&usqp=CAU"
    },
    {
      "id": "3badb9d4-c12d-4bdd-a74c-f403cc7525d6",
      "color": "Pink",
      "men": "true",
      "name": "Men's sweat shirt",
      "price": "500",
      "sizeL": "true",
      "sizeM": "true",
      "sizeS": "true",
      "url": "https://encrypted-tbn0.gstatic.com/images?q=tbn:ANd9GcQBugH7IYFg0jHwkwC-OUF_xNfrcC_Vle6oDZKW3oJO5XQBqh-It2PDfBBjeKOiklTSwHk&usqp=CAU"
    },
    {
      "id": "bbefc000-e253-48e6-98bb-157edd0018bd",
      "color": "Green",
      "men": "true",
      "name": "Men's sweat shirt",
      "price": "500",
      "sizeL": "true",
      "sizeM": "true",
      "sizeS": "true",
      "url": "https://encrypted-tbn0.gstatic.com/images?q=tbn:ANd9GcQnNRk0fd5zrjIeG-57pjsI2rbtJR6wYUgwn0dk1dc1PLTZq7mP_BpZnQJx7TMdymMqw0Y&usqp=CAU"
    },
    {
      "id": "c5fa96bb-25cb-4af0-adb4-37ce0c637061",
      "color": "Blue",
      "men": "true",
      "name": "Men's sweat shirt",
      "price": "450",
      "sizeL": "true",
      "sizeM": "true",
      "sizeS": "true",
      "url": "https://assets.ajio.com/medias/sys_master/root/20220702/vOt5/62bf3fa0aeb26921af596f79/-288Wx360H-441139544-green-MODEL.jpg"
    },
    {
      "id": "e1c05bb4-26c7-4e82-bfb0-9b4f207067a8",
      "color": "Grey",
      "men": "true",
      "name": "Men's sweat shirt",
      "price": "460",
      "sizeL": "",
      "sizeM": "",
      "sizeS": "true",
      "url": "https://static.nike.com/a/images/c_limit,w_592,f_auto/t_product_v1/79fc4125-9147-49bb-a94f-ec6b40fad727/air-jordan-wordmark-fleece-hoodie.png"
    },
    {
      "id": "358a3110-35e1-4b45-a696-df65ce439fe7",
      "color": "Green",
      "men": "true",
      "name": "Men's sweat shirt",
      "price": "600",
      "sizeL": "true",
      "sizeM": "true",
      "sizeS": "true",
      "url": "https://m.media-amazon.com/images/I/81twBBwYQrL._AC_UL320_.jpg"
    },
    {
      "id": "705d2be5-9b3b-4a68-b85f-ef88ab86ee1a",
      "color": "Brown",
      "men": "true",
      "name": "Men's sweat shirt",
      "price": "600",
      "sizeL": "true",
      "sizeM": "true",
      "sizeS": "true",
      "url": "https://assets.ajio.com/medias/sys_master/root/20220920/kUtX/6328c453f997dd1f8d08c598/john_players_jeans_sky_blue_%26_white_colourblock_slim_fit_sweatshirt.jpg"
    },
    {
      "id": "62d95676-a456-4344-b77d-afbd00ad1166",
      "color": "Purple",
      "men": "false",
      "name": "Women's t-shirt",
      "price": "400",
      "sizeL": "true",
      "sizeM": "true",
      "sizeS": "true",
      "url": "https://assets.myntassets.com/dpr_1.5,q_60,w_400,c_limit,fl_progressive/assets/images/13930788/2021/8/6/38d6c0e3-cda3-4059-a673-2cdb0bafae181628241011946-DILLINGER-Women-Tshirts-8941628241011571-1.jpg"
    },
    {
      "id": "080c8b74-7701-4933-b170-1d85dfb82b00",
      "color": "Pink",
      "men": "false",
      "name": "Over sized t-shirt",
      "price": "300",
      "sizeL": "true",
      "sizeM": "true",
      "sizeS": "true",
      "url": "https://encrypted-tbn0.gstatic.com/images?q=tbn:ANd9GcQ9tOPgss4AEb6ErA6V4zsxM0nBA969HPMkXxVi-KQbjA37s_W0O0KDIiU21_gZsyBSOQ4&usqp=CAU"
    },
    {
      "id": "3739ec69-bc59-4b6d-97a6-2c5100e01fd9",
      "color": "Purple",
      "men": "false",
      "name": "Over sized t-shirt",
      "price": "400",
      "sizeL": "true",
      "sizeM": "true",
      "sizeS": "true",
      "url": "https://encrypted-tbn0.gstatic.com/images?q=tbn:ANd9GcQvJ0_DmD14ue2e_9yr05s5aHAj_Gq9ilmcvmU4yCRy9XOiTbI6KVAA5jrRwjOXzhARCK8&usqp=CAU"
    },
    {
      "id": "a84e0092-848e-4e4e-ae9f-1bc5dfab5255",
      "color": "white",
      "men": "false",
      "name": "Over sized t-shirt",
      "price": "400",
      "sizeL": "true",
      "sizeM": "true",
      "sizeS": "true",
      "url": "https://encrypted-tbn0.gstatic.com/images?q=tbn:ANd9GcT5Ro-4E4xwU_ovFmRAzJkXHoV4EeE5o8q-jgr9qcTjvUKYyOBso5zhF1Al72hWWxi7-Tw&usqp=CAU"
    },
    {
      "id": "92a78345-d91a-4c5a-82a1-3e26279d1b50",
      "color": "Black",
      "men": "false",
      "name": "Over sized t-shirt",
      "price": "400",
      "sizeL": "true",
      "sizeM": "true",
      "sizeS": "true",
      "url": " https://encrypted-tbn0.gstatic.com/images?q=tbn:ANd9GcT-B0TMt5FnqWb8UZ4WSECR9R5epwMQswjggHKHbTShsoujTQNbHVhALlDm7gzBnvGvkrM&usqp=CAU"
    },
    {
      "id": "43aead50-88bf-4276-94ec-8b60ef1eb4ca",
      "color": "Black",
      "men": "false",
      "name": " Over sized t-shirt",
      "price": "500",
      "sizeL": "",
      "sizeM": "",
      "sizeS": "true",
      "url": "https://encrypted-tbn0.gstatic.com/images?q=tbn:ANd9GcT-B0TMt5FnqWb8UZ4WSECR9R5epwMQswjggHKHbTShsoujTQNbHVhALlDm7gzBnvGvkrM&usqp=CAU"
    },
    {
      "id": "145116e9-13b4-4e05-9915-18633603b497",
      "color": "Brown",
      "men": "false",
      "name": "Over sized t-shirt",
      "price": "340",
      "sizeL": "true",
      "sizeM": "true",
      "sizeS": "true",
      "url": "https://encrypted-tbn0.gstatic.com/images?q=tbn:ANd9GcSXuRdx700jr2ThfQBPbCvaHvwWjsDEtiUARpQ67Cb6lluaDe9oBjCoakmbL7R7HwPIZUM&usqp=CAU"
    },
    {
      "id": "e6aabc21-619f-4b3a-a75c-882ed67a92c2",
      "color": "Yellow",
      "men": "false",
      "name": "Over sized t-shirt",
      "price": "400",
      "sizeL": "true",
      "sizeM": "true",
      "sizeS": "true",
      "url": "https://encrypted-tbn0.gstatic.com/images?q=tbn:ANd9GcSPom3r8oWthvNhx52T6MMDbGo1tZMff6dGWM-YwAZP2zchMJuDvDDqa_1KisHQzEoaeY8&usqp=CAU"
    },
    {
      "id": "5f94bf7d-6cfa-456b-9c3e-302ac6da25de",
      "color": "Grey",
      "men": "false",
      "name": "Over sized t-shirt",
      "price": "500",
      "sizeL": "true",
      "sizeM": "true",
      "sizeS": "true",
      "url": "https://encrypted-tbn0.gstatic.com/images?q=tbn:ANd9GcQfkk15tSQR4T6kD0KWRys64zad7VOzxTOzfSucvGsCqqq6UDymJv7dYGWy-4vulsctIY0&usqp=CAU"
    },
    {
      "id": "cd1d498f-a77c-483d-bcd3-6266f81c17ed",
      "color": "Green",
      "men": "false",
      "name": "Women's t-shirt",
      "price": "400",
      "sizeL": "true",
      "sizeM": "true",
      "sizeS": "true",
      "url": "https://assets.myntassets.com/dpr_1.5,q_60,w_400,c_limit,fl_progressive/assets/images/10968502/2020/2/18/54c26fb8-d8c6-42b0-a3d6-eea009aaba161582020847616-Roadster-Women-Tshirts-2671582020846188-1.jpg"
    },
    {
      "id": "34373fe5-73ee-46f8-bea3-77ecc33e6c1f",
      "color": "Yellow",
      "men": "false",
      "name": "Women's t-shirt",
      "price": "450",
      "sizeL": "true",
      "sizeM": "true",
      "sizeS": "true",
      "url": "https://www.beyoung.in/api/cache/catalog/products/printed_t-shirt_girl_final_16_9_2022/overthinker_mustard_t-shirt_for_girls_base_400x533.jpg"
    },
    {
      "id": "bf58a5c0-7fc2-4bdf-9c0b-72c7c6846a3c",
      "color": "Black",
      "men": "false",
      "name": "Women's t-shirt",
      "price": "400",
      "sizeL": "true",
      "sizeM": "true",
      "sizeS": "true",
      "url": " https://cdn.shopify.com/s/files/1/0266/6276/4597/products/300920711BLACK_1.jpg?v=1664015226"
    },
    {
      "id": "9499c696-264d-4fec-9594-129f84d7e7b8",
      "color": "Grey",
      "men": "false",
      "name": "Sweat shirt",
      "price": "450",
      "sizeL": "true",
      "sizeM": "true",
      "sizeS": "true",
      "url": "https://n2.sdlcdn.com/imgs/k/f/p/230X258_sharpened/JUNEBERRY-Cotton-Multi-Color-T-SDL485779609-1-afcc4.jpg"
    },
    {
      "id": "1cb1ce28-da3a-448c-8330-cdf445bf4f0c",
      "color": "Black",
      "men": "false",
      "name": "black sweat shirt",
      "price": "420",
      "sizeL": "true",
      "sizeM": "true",
      "sizeS": "true",
      "url": "https://m.media-amazon.com/images/I/61SURmeW9PL._UY550_.jpg"
    },
    {
      "id": "e494b525-5a61-4b50-9b38-b0a0c3323994",
      "color": "Black",
      "men": "false",
      "name": "Women's t-shirt",
      "price": "400",
      "sizeL": "true",
      "sizeM": "true",
      "sizeS": "true",
      "url": "https://encrypted-tbn0.gstatic.com/images?q=tbn:ANd9GcSM043mJdpyOs4_Pr0iMTvpEuw_w-uQ5_eKp6g4HBQLKgvbZgYpQIe_dFddsjA0pbUGhb0&usqp=CAU"
    },
    {
      "id": "a50555f9-f0c6-4de7-b9bf-4473d1164aea",
      "color": "Black",
      "men": "false",
      "name": "Sweat shirt",
      "price": "500",
      "sizeL": "true",
      "sizeM": "true",
      "sizeS": "true",
      "url": "https://cdn.shopify.com/s/files/1/2360/8505/products/Full-Sleeve-Top-In-Black-White-And-Green_295x.jpg?v=1559837615"
    },
    {
      "id": "c1fa4c87-efb3-40a9-93dd-76de1c1f05e6",
      "color": "Green",
      "men": "false",
      "name": "Over sized t-shirt",
      "price": "400",
      "sizeL": "true",
      "sizeM": "true",
      "sizeS": "true",
      "url": "https://prod-img.thesouledstore.com/public/theSoul/uploads/catalog/product/1666773358_8922491.jpg"
    },
    {
      "id": "8777a62c-424e-49c7-bcfa-900892f5a088",
      "color": "Green",
      "men": "false",
      "name": "Over sized t-shirt",
      "price": "500",
      "sizeL": "true",
      "sizeM": "true",
      "sizeS": "true",
      "url": "https://images-eu.ssl-images-amazon.com/images/I/61sQ0kQuu2L._AC._SR360,460.jpg"
    },
    {
      "id": "61ac5a9f-6dc9-4751-baf5-533548f16c6d",
      "color": "Orange",
      "men": "false",
      "name": "Sweat shirt",
      "price": "600",
      "sizeL": "true",
      "sizeM": "true",
      "sizeS": "true",
      "url": "https://target.scene7.com/is/image/Target/GUEST_01c5089a-6654-4400-96b5-7ebf39ead047"
    },
    {
      "id": "89205d47-fc65-4c93-bd5b-93fd8a284024",
      "color": "White",
      "men": "false",
      "name": "Women's t-shirt",
      "price": "400",
      "sizeL": "true",
      "sizeM": "true",
      "sizeS": "true",
      "url": "https://i0.wp.com/sourcingjournal.com/wp-content/uploads/2020/07/womens-Asos.png"
    },
    {
      "id": "2146091b-93c5-42aa-a8c3-6c8ca5eba411",
      "color": "Yellow",
      "men": "false",
      "name": "Women's t-shirt",
      "price": "400",
      "sizeL": "true",
      "sizeM": "true",
      "sizeS": "true",
      "url": "https://encrypted-tbn0.gstatic.com/images?q=tbn:ANd9GcSSkRjozBzkxl_l30uN8nFP_gS1mTqEpZ15Rw-odMFpXaqCD1fDCCyanBRKCeeGHDESdws&usqp=CAU"
    },
    {
      "id": "6ca94fda-56d4-4752-9779-748dc211c042",
      "color": "Pink",
      "men": "false",
      "name": "Women's t-shirt",
      "price": "300",
      "sizeL": "true",
      "sizeM": "true",
      "sizeS": "true",
      "url": "https://assetscdn1.paytm.com/images/catalog/product/A/AP/APPBESIVA-WOMENBESI2576676FB9283/1563446319496_0..jpg?imwidth=282&impolicy=hq"
    },
    {
      "id": "a85cafe8-2415-4964-9e1e-cbd78862e569",
      "color": "Red",
      "men": "false",
      "name": "Sweat shirt",
      "price": "550",
      "sizeL": false,
      "sizeM": "true",
      "sizeS": "true",
      "url": " https://encrypted-tbn0.gstatic.com/images?q=tbn:ANd9GcTAHfXFBvzOc0-d1q6SSCcnr9VgFfcP2x74PAGdMMdTljI4R2m_-Mpm7staVFKeXzF_vaM&usqp=CAU"
    },
    {
      "color": "blue",
      "men": "true",
      "name": "silk blue mens",
      "price": "5665",
      "sizeL": "",
      "sizeM": "",
      "sizeS": "true",
      "url": "https://imgs.search.brave.com/GDnCjqNmYh8T3J4gk0Yk9cBmswoUiZRGCGCStWqnBF8/rs:fit:500:0:0:0/g:ce/aHR0cHM6Ly9jb250/ZW50Lm1vc3MuY28u/dWsvaW1hZ2VzL2V4/dHJhZXh0cmFsYXJn/ZS85NjY4MDY5OTFf/MDEuanBn",
      "id": "1AP5Dw4"
    },
    {
      "color": "dark blue",
      "men": "true",
      "name": "Dark blue shirt",
      "price": "250",
      "sizeL": "true",
      "sizeM": "true",
      "sizeS": "true",
      "url": "https://imgs.search.brave.com/FgT8GodkTLMlghgHn1gCRf6A0ESFEbDnHXfQXl1bBBg/rs:fit:860:0:0:0/g:ce/aHR0cHM6Ly9pLnBp/bmltZy5jb20vb3Jp/Z2luYWxzLzM5Lzcw/LzY2LzM5NzA2NjYx/ZWIzNWM1MWY4ZTNk/NzFhMWZhOGVkNjU0/LmpwZw",
      "id": "7z0RySI"
    },
    {
      "color": "Black",
      "men": "true",
      "name": "Dark black T shirt",
      "price": "150",
      "sizeL": "true",
      "sizeM": "true",
      "sizeS": "true",
      "url": "https://imgs.search.brave.com/7R_xDqxszla4R1w-pdmPZ9YettgORtYB4loWhvBc4KY/rs:fit:860:0:0:0/g:ce/aHR0cHM6Ly9tZWRp/YS5pc3RvY2twaG90/by5jb20vaWQvOTQy/OTM3NDU4L3Bob3Rv/L3Qtc2hpcnQtZGVz/aWduLWFuZC1wZW9w/bGUtY29uY2VwdC1j/bG9zZS11cC1vZi15/b3VuZy1tYW4taW4t/YmxhbmstYmxhY2st/dC1zaGlydC1zaGly/dC1mcm9udC1hbmQu/anBnP3M9NjEyeDYx/MiZ3PTAmaz0yMCZj/PTYydHZpakM2aHRG/bWxTWFBXM3hUVlZV/RnlWSU03eVUySXVr/TzRYa0hQZjA9",
      "id": "s7U9vOQ"
    }
  ],
  "cart": [
    {
      "id": "a84e0092-848e-4e4e-ae9f-1bc5dfab5255",
      "color": "white",
      "men": "false",
      "name": "Over sized t-shirt",
      "price": "400",
      "sizeL": "true",
      "sizeM": "true",
      "sizeS": "true",
      "url": "https://encrypted-tbn0.gstatic.com/images?q=tbn:ANd9GcT5Ro-4E4xwU_ovFmRAzJkXHoV4EeE5o8q-jgr9qcTjvUKYyOBso5zhF1Al72hWWxi7-Tw&usqp=CAU",
      "quantity": 1
    },
    {
      "id": "db82ab22-1119-465c-879c-ce2321b5059d",
      "color": "Blue",
      "men": "true",
      "name": "Men's t-shirt Blue",
      "price": "400",
      "sizeL": "true",
      "sizeM": "true",
      "sizeS": "true",
      "url": "https://assets.ajio.com/medias/sys_master/root/20220121/XQUl/61ea5b98aeb2695cdd2466db/-473Wx593H-461575346-blue-MODEL.jpg",
      "quantity": 1
    },
    {
      "id": "a17f8a96-9016-45ac-a4f0-b628eb90d620",
      "color": "Yellow",
      "men": "true",
      "name": "Men's plain yellow t-shirt",
      "price": "450",
      "sizeL": "true",
      "sizeM": "true",
      "sizeS": "true",
      "url": "https://m.media-amazon.com/images/I/514Ibqp2XZL._UX569_.jpg",
      "quantity": 1
    },
    {
      "id": "129abbea-b19d-40ee-bc83-b0efcdbd93fc",
      "color": "Black",
      "men": "true",
      "name": "Oversized t-shirt",
      "price": "400",
      "sizeL": "",
      "sizeM": "true",
      "sizeS": "true",
      "url": "https://m.media-amazon.com/images/I/71QvZzrovaL._UL1500_.jpg",
      "quantity": 1
    },
    {
      "id": "3739ec69-bc59-4b6d-97a6-2c5100e01fd9",
      "color": "Purple",
      "men": "false",
      "name": "Over sized t-shirt",
      "price": "400",
      "sizeL": "true",
      "sizeM": "true",
      "sizeS": "true",
      "url": "https://encrypted-tbn0.gstatic.com/images?q=tbn:ANd9GcQvJ0_DmD14ue2e_9yr05s5aHAj_Gq9ilmcvmU4yCRy9XOiTbI6KVAA5jrRwjOXzhARCK8&usqp=CAU",
      "quantity": 1
    }
  ]
}